odscli/__init__.py
odscli/ods_cli.py
odscli/sdk/__init__.py
odscli/sdk/carbon_scheduler.py
odscli/sdk/carbon_scheduler_gui.py
odscli/sdk/constants.py
odscli/sdk/credential.py
odscli/sdk/endpoint_management.py
odscli/sdk/ftn_nodes.py
odscli/sdk/log.py
odscli/sdk/login.py
odscli/sdk/measure.py
odscli/sdk/meta_query.py
odscli/sdk/meta_query_gui.py
odscli/sdk/query_transfer_data.py
odscli/sdk/scheduler.py
odscli/sdk/token_utils.py
odscli/sdk/metrics/__init__.py
odscli/sdk/metrics/measure_carbon.py
odscli/sdk/metrics/measure_host_network.py
odscli/sdk/metrics/metrics_pojo.py
odscli-1.1.5.dist-info/METADATA
odscli-1.1.5.dist-info/WHEEL
odscli-1.1.5.dist-info/entry_points.txt
odscli-1.1.5.dist-info/top_level.txt
odscli-1.1.5.dist-info/RECORD
